libtapedrive/__init__.py
libtapedrive/downloads.py
libtapedrive/podcast.py
libtapedrive-0.1.1.dist-info/WHEEL
libtapedrive-0.1.1.dist-info/METADATA
libtapedrive-0.1.1.dist-info/RECORD
