Metadata-Version: 2.1
Name: libtapedrive
Version: 0.1.1
Summary: Podcast client library for feed parsing
Home-page: https://tapedrive.io/lib
License: Apache-2.0
Author: Jan Willhaus
Author-email: mail@janwillhaus.de
Requires-Python: >=3.7,<4.0
Classifier: Development Status :: 1 - Planning
Classifier: Intended Audience :: Developers
Classifier: License :: OSI Approved :: Apache Software License
Classifier: Operating System :: POSIX
Classifier: Programming Language :: Python :: 3
Classifier: Programming Language :: Python :: 3 :: Only
Classifier: Programming Language :: Python :: 3.7
Classifier: Topic :: Software Development :: Libraries :: Python Modules
Classifier: Topic :: Utilities
Requires-Dist: beautifulsoup4 (>=4.7,<5.0)
Requires-Dist: bleach (>=3.1,<4.0)
Requires-Dist: enlighten (>=1.3,<2.0)
Requires-Dist: feedparser (>=5.2,<6.0)
Requires-Dist: html5lib (>=1.0,<2.0)
Requires-Dist: pillow (>=6.0,<7.0)
Requires-Dist: python-dateutil (>=2.8,<3.0)
Requires-Dist: requests (>=2.21,<3.0)
Project-URL: Documentation, https://libtapedrive.readthedocs.io/en/latest/
Project-URL: Repository, https://github.com/janw/libtapedrive
